talos_linux_api/v1_3_0/__init__.py
talos_linux_api/v1_3_0/cluster/__init__.py
talos_linux_api/v1_3_0/common/__init__.py
talos_linux_api/v1_3_0/google/__init__.py
talos_linux_api/v1_3_0/google/rpc/__init__.py
talos_linux_api/v1_3_0/inspect/__init__.py
talos_linux_api/v1_3_0/machine/__init__.py
talos_linux_api/v1_3_0/resource/__init__.py
talos_linux_api/v1_3_0/resource/config/__init__.py
talos_linux_api/v1_3_0/resource/network/__init__.py
talos_linux_api/v1_3_0/securityapi/__init__.py
talos_linux_api/v1_3_0/storage/__init__.py
talos_linux_api/v1_3_0/talos/__init__.py
talos_linux_api/v1_3_0/talos/resource/__init__.py
talos_linux_api/v1_3_0/talos/resource/definitions/__init__.py
talos_linux_api/v1_3_0/talos/resource/definitions/cluster/__init__.py
talos_linux_api/v1_3_0/talos/resource/definitions/cri/__init__.py
talos_linux_api/v1_3_0/talos/resource/definitions/enums/__init__.py
talos_linux_api/v1_3_0/talos/resource/definitions/etcd/__init__.py
talos_linux_api/v1_3_0/talos/resource/definitions/extensions/__init__.py
talos_linux_api/v1_3_0/talos/resource/definitions/files/__init__.py
talos_linux_api/v1_3_0/talos/resource/definitions/hardware/__init__.py
talos_linux_api/v1_3_0/talos/resource/definitions/k8s/__init__.py
talos_linux_api/v1_3_0/talos/resource/definitions/kubeaccess/__init__.py
talos_linux_api/v1_3_0/talos/resource/definitions/kubespan/__init__.py
talos_linux_api/v1_3_0/talos/resource/definitions/network/__init__.py
talos_linux_api/v1_3_0/talos/resource/definitions/perf/__init__.py
talos_linux_api/v1_3_0/talos/resource/definitions/proto/__init__.py
talos_linux_api/v1_3_0/talos/resource/definitions/runtime/__init__.py
talos_linux_api/v1_3_0/talos/resource/definitions/secrets/__init__.py
talos_linux_api/v1_3_0/talos/resource/definitions/time/__init__.py
talos_linux_api/v1_3_0/talos/resource/definitions/v1alpha1/__init__.py
talos_linux_api/v1_3_0/time/__init__.py
talos_linux_api_v1.3.0-0.1.0.dist-info/WHEEL
talos_linux_api_v1.3.0-0.1.0.dist-info/METADATA
talos_linux_api_v1.3.0-0.1.0.dist-info/licenses/LICENSE
talos_linux_api_v1.3.0-0.1.0.dist-info/RECORD
